i281_main/Control Logic/controllogic.v
/*
Control Logic: Uses the input opcodes and generates control signals.

op_in[26:25] = RX
op_in[24:23] = RY

Specifications:
Inputs: op_in (27-wide), flag_in (4-wide)
Outputs: ctrl_out (18-wide)
*/

module controllogic (
    input  wire [26:0] op_in,
    input  wire [ 3:0] flag_in,
    output reg  [1:18] ctrl_out
);

  always @(op_in, flag_in) begin
    ctrl_out = 18'b0;

    //c1
    if (|op_in[2:1]) ctrl_out[1] = 1;

    //c2
    if (op_in[22]) ctrl_out[2] = flag_in[0] ~^ flag_in[1];
    else if (op_in[21]) ctrl_out[2] = (~flag_in[2]) & (flag_in[0] ~^ flag_in[1]);
    else if (op_in[20]) ctrl_out[2] = ~flag_in[2];
    else if (op_in[19]) ctrl_out[2] = flag_in[2];
    else if (op_in[18]) ctrl_out[2] = 1;

    //c3
    ctrl_out[3] = 1;

    //c4,c5
    if (|{op_in[17:15], op_in[10:7], op_in[4], op_in[2]}) ctrl_out[4:5] = op_in[26:25];
    else if (op_in[12] | op_in[5]) ctrl_out[4:5] = op_in[24:23];

    //c6,c7
    if (|op_in[14:13]) ctrl_out[6:7] = op_in[26:25];
    else if (|{op_in[17], op_in[9], op_in[7]}) ctrl_out[6:7] = op_in[24:23];

    //c8,c9
    if (|{op_in[16:15], op_in[12:5]}) ctrl_out[8:9] = op_in[26:25];

    //c10
    if (|{op_in[16:15], op_in[12:5]}) ctrl_out[10] = 1;

    //c11
    if (|{op_in[14], op_in[12], op_in[10], op_in[8], op_in[5:4], op_in[2]}) ctrl_out[11] = 1;

    //c12
    if (|{op_in[17], op_in[14], op_in[12], op_in[10:7], op_in[5:4], op_in[2]}) ctrl_out[12] = 1;

    //c13
    if (|{op_in[17:16], op_in[10:9]}) ctrl_out[13] = 1;

    //c14
    if (|{op_in[17:15], op_in[10:7]}) ctrl_out[14] = 1;

    //c15
    if (|{op_in[13], op_in[11], op_in[6], op_in[3], op_in[1]}) ctrl_out[15] = 1;

    //c16
    if (|op_in[4:3]) ctrl_out[16] = 1;

    //c17
    if (|{op_in[14:13], op_in[4:3]}) ctrl_out[17] = 1;

    //c18
    if (|op_in[12:11]) ctrl_out[18] = 1;
  end

endmodule

i281_main/Control Logic/controllogic_tb.v
/*
Testbench for Control Logic Generator.
*/

`timescale 1ns / 1ps

module controllogic_tb ();

  // signal instantiation
  reg  [26:0] op_in;
  reg  [ 3:0] flag_in;
  wire [1:18] ctrl_out;

  // UUT instantiation
  controllogic uut (
      .op_in(op_in),
      .flag_in(flag_in),
      .ctrl_out(ctrl_out)
  );

  // Stimulus
  integer i, j, k;
  initial begin

    for (i = 0; i < 23; i++) begin
      op_in[22:0] = 23'b0;
      op_in[i] = 1;
      for (j = 0; j < 16; j++) begin
        op_in[26:23] = j;
        for (k = 0; k < 16; k++) begin
          flag_in = k;
          #10;
        end
      end
    end
    $finish;
  end

  // Variable Dump
  initial begin
    $dumpfile("dump.vcd");
    $dumpvars(0, controllogic_tb);
  end

endmodule

i281_multicycle_flag_reg/Control Logic/dump.vcd
$date
	Thu Nov 20 19:07:56 2025
$end
$version
	Icarus Verilog
$end
$timescale
	1ps
$end
$scope module controllogic_tb $end
$var wire 18 ! ctrl_out [1:18] $end
$var reg 4 " flag_in [3:0] $end
$var reg 27 # op_in [26:0] $end
$var integer 32 $ i [31:0] $end
$var integer 32 % j [31:0] $end
$var integer 32 & k [31:0] $end
$scope module uut $end
$var wire 4 ' flag_in [3:0] $end
$var wire 27 ( op_in [26:0] $end
$var reg 18 ) ctrl_out [1:18] $end
$upscope $end
$upscope $end
$enddefinitions $end
#0
$dumpvars
b1000000000000000 )
b1 (
b0 '
b0 &
b0 %
b0 $
b1 #
b0 "
b1000000000000000 !
$end
#10000
b1000000000000000 !
b1000000000000000 )
b1 "
b1 '
b1 &
#20000
b1000000000000000 !
b1000000000000000 )
b10 "
b10 '
b10 &
#30000
b1000000000000000 !
b1000000000000000 )
b11 "
b11 '
b11 &
#40000
b1000000000000000 !
b1000000000000000 )
b100 "
b100 '
b100 &
#50000
b1000000000000000 !
b1000000000000000 )
b101 "
b101 '
b101 &
#60000
b1000000000000000 !
b1000000000000000 )
b110 "
b110 '
b110 &
#70000
b1000000000000000 !
b1000000000000000 )
b111 "
b111 '
b111 &
#80000
b1000000000000000 !
b1000000000000000 )
b1000 "
b1000 '
b1000 &
#90000
b1000000000000000 !
b1000000000000000 )
b1001 "
b1001 '
b1001 &
#100000
b1000000000000000 !
b1000000000000000 )
b1010 "
b1010 '
b1010 &
#110000
b1000000000000000 !
b1000000000000000 )
b1011 "
b1011 '
b1011 &
#120000
b1000000000000000 !
b1000000000000000 )
b1100 "
b1100 '
b1100 &
#130000
b1000000000000000 !
b1000000000000000 )
b1101 "
b1101 '
b1101 &
#140000
b1000000000000000 !
b1000000000000000 )
b1110 "
b1110 '
b1110 &
#150000
b1000000000000000 !
b1000000000000000 )
b1111 "
b1111 '
b1111 &
#160000
b1000000000000000 !
b1000000000000000 )
b0 "
b0 '
b100000000000000000000001 #
b100000000000000000000001 (
b1 %
b0 &
#170000
b1000000000000000 !
b1000000000000000 )
b1 "
b1 '
b1 &
#180000
b1000000000000000 !
b1000000000000000 )
b10 "
b10 '
b10 &
#190000
b1000000000000000 !
b1000000000000000 )
b11 "
b11 '
b11 &
#200000
b1000000000000000 !
b1000000000000000 )
b100 "
b100 '
b100 &
#210000
b1000000000000000 !
b1000000000000000 )
b101 "
b101 '
b101 &
#220000
b1000000000000000 !
b1000000000000000 )
b110 "
b110 '
b110 &
#230000
b1000000000000000 !
b1000000000000000 )
b111 "
b111 '
b111 &
#240000
b1000000000000000 !
b1000000000000000 )
b1000 "
b1000 '
b1000 &
#250000
b1000000000000000 !
b1000000000000000 )
b1001 "
b1001 '
b1001 &
#260000
b1000000000000000 !
b1000000000000000 )
b1010 "
b1010 '
b1010 &
#270000
b1000000000000000 !
b1000000000000000 )
b1011 "
b1011 '
b1011 &
#280000
b1000000000000000 !
b1000000000000000 )
b1100 "
b1100 '
b1100 &
#290000
b1000000000000000 !
b1000000000000000 )
b1101 "
b1101 '
b1101 &
#300000
b1000000000000000 !
b1000000000000000 )
b1110 "
b1110 '
b1110 &
#310000
b1000000000000000 !
b1000000000000000 )
b1111 "
b1111 '
b1111 &
#320000
b1000000000000000 !
b1000000000000000 )
b0 "
b0 '
b1000000000000000000000001 #
b1000000000000000000000001 (
b10 %
b0 &
#330000
b1000000000000000 !
b1000000000000000 )
b1 "
b1 '
b1 &
#340000
b1000000000000000 !
b1000000000000000 )
b10 "
b10 '
b10 &
#350000
b1000000000000000 !
b1000000000000000 )
b11 "
b11 '
b11 &
#360000
b1000000000000000 !
b1000000000000000 )
b100 "
b100 '
b100 &
#370000
b1000000000000000 !
b1000000000000000 )
b101 "
b101 '
b101 &
#380000
b1000000000000000 !
b1000000000000000 )
b110 "
b110 '
b110 &
#390000
b1000000000000000 !
b1000000000000000 )
b111 "
b111 '
b111 &
#400000
b1000000000000000 !
b1000000000000000 )
b1000 "
b1000 '
b1000 &
#410000
b1000000000000000 !
b1000000000000000 )
b1001 "
b1001 '
b1001 &
#420000
b1000000000000000 !
b1000000000000000 )
b1010 "
b1010 '
b1010 &
#430000
b1000000000000000 !
b1000000000000000 )
b1011 "
b1011 '
b1011 &
#440000
b1000000000000000 !
b1000000000000000 )
b1100 "
b1100 '
b1100 &
#450000
b1000000000000000 !
b1000000000000000 )
b1101 "
b1101 '
b1101 &
#460000
b1000000000000000 !
b1000000000000000 )
b1110 "
b1110 '
b1110 &
#470000
b1000000000000000 !
b1000000000000000 )
b1111 "
b1111 '
b1111 &
#480000
b1000000000000000 !
b1000000000000000 )
b0 "
b0 '
b1100000000000000000000001 #
b1100000000000000000000001 (
b11 %
b0 &
#490000
b1000000000000000 !
b1000000000000000 )
b1 "
b1 '
b1 &
#500000
b1000000000000000 !
b1000000000000000 )
b10 "
b10 '
b10 &
#510000
b1000000000000000 !
b1000000000000000 )
b11 "
b11 '
b11 &
#520000
b1000000000000000 !
b1000000000000000 )
b100 "
b100 '
b100 &
#530000
b1000000000000000 !
b1000000000000000 )
b101 "
b101 '
b101 &
#540000
b1000000000000000 !
b1000000000000000 )
b110 "
b110 '
b110 &
#550000
b1000000000000000 !
b1000000000000000 )
b111 "
b111 '
b111 &
#560000
b1000000000000000 !
b1000000000000000 )
b1000 "
b1000 '
b1000 &
#570000
b1000000000000000 !
b1000000000000000 )
b1001 "
b1001 '
b1001 &
#580000
b1000000000000000 !
b1000000000000000 )
b1010 "
b1010 '
b1010 &
#590000
b1000000000000000 !
b1000000000000000 )
b1011 "
b1011 '
b1011 &
#600000
b1000000000000000 !
b1000000000000000 )
b1100 "
b1100 '
b1100 &
#610000
b1000000000000000 !
b1000000000000000 )
b1101 "
b1101 '
b1101 &
#620000
b1000000000000000 !
b1000000000000000 )
b1110 "
b1110 '
b1110 &
#630000
b1000000000000000 !
b1000000000000000 )
b1111 "
b1111 '
b1111 &
#640000
b1000000000000000 !
b1000000000000000 )
b0 "
b0 '
b10000000000000000000000001 #
b10000000000000000000000001 (
b100 %
b0 &
#650000
b1000000000000000 !
b1000000000000000 )
b1 "
b1 '
b1 &
#660000
b1000000000000000 !
b1000000000000000 )
b10 "
b10 '
b10 &
#670000
b1000000000000000 !
b1000000000000000 )
b11 "
b11 '
b11 &
#680000
b1000000000000000 !
b1000000000000000 )
b100 "
b100 '
b100 &
#690000
b1000000000000000 !
b1000000000000000 )
b101 "
b101 '
b101 &
#700000
b1000000000000000 !
b1000000000000000 )
b110 "
b110 '
b110 &
#710000
b1000000000000000 !
b1000000000000000 )
b111 "
b111 '
b111 &
#720000
b1000000000000000 !
b1000000000000000 )
b1000 "
b1000 '
b1000 &
#730000
b1000000000000000 !
b1000000000000000 )
b1001 "
b1001 '
b1001 &
#740000
b1000000000000000 !
b1000000000000000 )
b1010 "
b1010 '
b1010 &
#750000
b1000000000000000 !
b1000000000000000 )
b1011 "
b1011 '
b1011 &
#760000
b1000000000000000 !
b1000000000000000 )
b1100 "
b1100 '
b1100 &
#770000
b1000000000000000 !
b1000000000000000 )
b1101 "
b1101 '
b1101 &
#780000
b1000000000000000 !
b1000000000000000 )
b1110 "
b1110 '
b1110 &
#790000
b1000000000000000 !
b1000000000000000 )
b1111 "
b1111 '
b1111 &
#800000
b1000000000000000 !
b1000000000000000 )
b0 "
b0 '
b10100000000000000000000001 #
b10100000000000000000000001 (
b101 %
b0 &
#810000
b1000000000000000 !
b1000000000000000 )
b1 "
b1 '
b1 &
#820000
b1000000000000000 !
b1000000000000000 )
b10 "
b10 '
b10 &
#830000
b1000000000000000 !
b1000000000000000 )
b11 "
b11 '
b11 &
#840000
b1000000000000000 !
b1000000000000000 )
b100 "
b100 '
b100 &
#850000
b1000000000000000 !
b1000000000000000 )
b101 "
b101 '
b101 &
#860000
b1000000000000000 !
b1000000000000000 )
b110 "
b110 '
b110 &
#870000
b1000000000000000 !
b1000000000000000 )
b111 "
b111 '
b111 &
#880000
b1000000000000000 !
b1000000000000000 )
b1000 "
b1000 '
b1000 &
#890000
b1000000000000000 !
b1000000000000000 )
b1001 "
b1001 '
b1001 &
#900000
b1000000000000000 !
b1000000000000000 )
b1010 "
b1010 '
b1010 &
#910000
b1000000000000000 !
b1000000000000000 )
b1011 "
b1011 '
b1011 &
#920000
b1000000000000000 !
b1000000000000000 )
b1100 "
b1100 '
b1100 &
#930000
b1000000000000000 !
b1000000000000000 )
b1101 "
b1101 '
b1101 &
#940000
b1000000000000000 !
b1000000000000000 )
b1110 "
b1110 '
b1110 &
#950000
b1000000000000000 !
b1000000000000000 )
b1111 "
b1111 '
b1111 &
#960000
b1000000000000000 !
b1000000000000000 )
b0 "
b0 '
b11000000000000000000000001 #
b11000000000000000000000001 (
b110 %
b0 &
#970000
b1000000000000000 !
b1000000000000000 )
b1 "
b1 '
b1 &
#980000
b1000000000000000 !
b1000000000000000 )
b10 "
b10 '
b10 &
#990000
b1000000000000000 !
b1000000000000000 )
b11 "
b11 '
b11 &
#1000000
b1000000000000000 !
b1000000000000000 )
b100 "
b100 '
b100 &
#1010000
b1000000000000000 !
b1000000000000000 )
b101 "
b101 '
b101 &
#1020000
b1000000000000000 !
b1000000000000000 )
b110 "
b110 '
b110 &
#1030000
b1000000000000000 !
b1000000000000000 )
b111 "
b111 '
b111 &
#1040000
b1000000000000000 !
b1000000000000000 )
b1000 "
b1000 '
b1000 &
#1050000
b1000000000000000 !
b1000000000000000 )
b1001 "
b1001 '
b1001 &
#1060000
b1000000000000000 !
b1000000000000000 )
b1010 "
b1010 '
b1010 &
#1070000
b1000000000000000 !
b1000000000000000 )
b1011 "
b1011 '
b1011 &
#1080000
b1000000000000000 !
b1000000000000000 )
b1100 "
b1100 '
b1100 &
#1090000
b1000000000000000 !
b1000000000000000 )
b1101 "
b1101 '
b1101 &
#1100000
b1000000000000000 !
b1000000000000000 )
b1110 "
b1110 '
b1110 &
#1110000
b1000000000000000 !
b1000000000000000 )
b1111 "
b1111 '
b1111 &
#1120000
b1000000000000000 !
b1000000000000000 )
b0 "
b0 '
b11100000000000000000000001 #
b11100000000000000000000001 (
b111 %
b0 &
#1130000
b1000000000000000 !
b1000000000000000 )
b1 "
b1 '
b1 &
#1140000
b1000000000000000 !
b1000000000000000 )
b10 "
b10 '
b10 &
#1150000
b1000000000000000 !
b1000000000000000 )
b11 "
b11 '
b11 &
#1160000
b1000000000000000 !
b1000000000000000 )
b100 "
b100 '
b100 &
#1170000
b1000000000000000 !
b1000000000000000 )
b101 "
b101 '
b101 &
#1180000
b1000000000000000 !
b1000000000000000 )
b110 "
b110 '
b110 &
#1190000
b1000000000000000 !
b1000000000000000 )
b111 "
b111 '
b111 &
#1200000
b1000000000000000 !
b1000000000000000 )
b1000 "
b1000 '
b1000 &
#1210000
b1000000000000000 !
b1000000000000000 )
b1001 "
b1001 '
b1001 &
#1220000
b1000000000000000 !
b1000000000000000 )
b1010 "
b1010 '
b1010 &
#1230000
b1000000000000000 !
b1000000000000000 )
b1011 "
b1011 '
b1011 &
#1240000
b1000000000000000 !
b1000000000000000 )
b1100 "
b1100 '
b1100 &
#1250000
b1000000000000000 !
b1000000000000000 )
b1101 "
b1101 '
b1101 &
#1260000
b1000000000000000 !
b1000000000000000 )
b1110 "
b1110 '
b1110 &
#1270000
b1000000000000000 !
b1000000000000000 )
b1111 "
b1111 '
b1111 &
#1280000
b1000000000000000 !
b1000000000000000 )
b0 "
b0 '
b100000000000000000000000001 #
b100000000000000000000000001 (
b1000 %
b0 &
#1290000
b1000000000000000 !
b1000000000000000 )
b1 "
b1 '
b1 &
#1300000
b1000000000000000 !
b1000000000000000 )
b10 "
b10 '
b10 &
#1310000
b1000000000000000 !
b1000000000000000 )
b11 "
b11 '
b11 &
#1320000
b1000000000000000 !
b1000000000000000 )
b100 "
b100 '
b100 &
#1330000
b1000000000000000 !
b1000000000000000 )
b101 "
b101 '
b101 &
#1340000
b1000000000000000 !
b1000000000000000 )
b110 "
b110 '
b110 &
#1350000
b1000000000000000 !
b1000000000000000 )
b111 "
b111 '
b111 &
#1360000
b1000000000000000 !
b1000000000000000 )
b1000 "
b1000 '
b1000 &
#1370000
b1000000000000000 !
b1000000000000000 )
b1001 "
b1001 '
b1001 &
#1380000
b1000000000000000 !
b1000000000000000 )
b1010 "
b1010 '
b1010 &
#1390000
b1000000000000000 !
b1000000000000000 )
b1011 "
b1011 '
b1011 &
#1400000
b1000000000000000 !
b1000000000000000 )
b1100 "
b1100 '
b1100 &
#1410000
b1000000000000000 !
b1000000000000000 )
b1101 "
b1101 '
b1101 &
#1420000
b1000000000000000 !
b1000000000000000 )
b1110 "
b1110 '
b1110 &
#1430000
b1000000000000000 !
b1000000000000000 )
b1111 "
b1111 '
b1111 &
#1440000
b1000000000000000 !
b1000000000000000 )
b0 "
b0 '
b100100000000000000000000001 #
b100100000000000000000000001 (
b1001 %
b0 &
#1450000
b1000000000000000 !
b1000000000000000 )
b1 "
b1 '
b1 &
#1460000
b1000000000000000 !
b1000000000000000 )
b10 "
b10 '
b10 &
#1470000
b1000000000000000 !
b1000000000000000 )
b11 "
b11 '
b11 &
#1480000
b1000000000000000 !
b1000000000000000 )
b100 "
b100 '
b100 &
#1490000
b1000000000000000 !
b1000000000000000 )
b101 "
b101 '
b101 &
#1500000
b1000000000000000 !
b1000000000000000 )
b110 "
b110 '
b110 &
#1510000
b1000000000000000 !
b1000000000000000 )
b111 "
b111 '
b111 &
#1520000
b1000000000000000 !
b1000000000000000 )
b1000 "
b1000 '
b1000 &
#1530000
b1000000000000000 !
b1000000000000000 )
b1001 "
b1001 '
b1001 &
#1540000
b1000000000000000 !
b1000000000000000 )
b1010 "
b1010 '
b1010 &
#1550000
b1000000000000000 !
b1000000000000000 )
b1011 "
b1011 '
b1011 &
#1560000
b1000000000000000 !
b1000000000000000 )
b1100 "
b1100 '
b1100 &
#1570000
b1000000000000000 !
b1000000000000000 )
b1101 "
b1101 '
b1101 &
#1580000
b1000000000000000 !
b1000000000000000 )
b1110 "
b1110 '
b1110 &
#1590000
b1000000000000000 !
b1000000000000000 )
b1111 "
b1111 '
b1111 &
#1600000
b1000000000000000 !
b1000000000000000 )
b0 "
b0 '
b101000000000000000000000001 #
b101000000000000000000000001 (
b1010 %
b0 &
#1610000
b1000000000000000 !
b1000000000000000 )
b1 "
b1 '
b1 &
#1620000
b1000000000000000 !
b1000000000000000 )
b10 "
b10 '
b10 &
#1630000
b1000000000000000 !
b1000000000000000 )
b11 "
b11 '
b11 &
#1640000
b1000000000000000 !
b1000000000000000 )
b100 "
b100 '
b100 &
#1650000
b1000000000000000 !
b1000000000000000 )
b101 "
b101 '
b101 &
#1660000
b1000000000000000 !
b1000000000000000 )
b110 "
b110 '
b110 &
#1670000
b1000000000000000 !
b1000000000000000 )
b111 "
b111 '
b111 &
#1680000
b1000000000000000 !
b1000000000000000 )
b1000 "
b1000 '
b1000 &
#1690000
b1000000000000000 !
b1000000000000000 )
b1001 "
b1001 '
b1001 &
#1700000
b1000000000000000 !
b1000000000000000 )
b1010 "
b1010 '
b1010 &
#1710000
b1000000000000000 !
b1000000000000000 )
b1011 "
b1011 '
b1011 &
#1720000
b1000000000000000 !
b1000000000000000 )
b1100 "
b1100 '
b1100 &
#1730000
b1000000000000000 !
b1000000000000000 )
b1101 "
b1101 '
b1101 &
#1740000
b1000000000000000 !
b1000000000000000 )
b1110 "
b1110 '
b1110 &
#1750000
b1000000000000000 !
b1000000000000000 )
b1111 "
b1111 '
b1111 &
#1760000
b1000000000000000 !
b1000000000000000 )
b0 "
b0 '
b101100000000000000000000001 #
b101100000000000000000000001 (
b1011 %
b0 &
#1770000
b1000000000000000 !
b1000000000000000 )
b1 "
b1 '
b1 &
#1780000
b1000000000000000 !
b1000000000000000 )
b10 "
b10 '
b10 &
#1790000
b1000000000000000 !
b1000000000000000 )
b11 "
b11 '
b11 &
#1800000
b1000000000000000 !
b1000000000000000 )
b100 "
b100 '
b100 &
#1810000
b1000000000000000 !
b1000000000000000 )
b101 "
b101 '
b101 &
#1820000
b1000000000000000 !
b1000000000000000 )
b110 "
b110 '
b110 &
#1830000
b1000000000000000 !
b1000000000000000 )
b111 "
b111 '
b111 &
#1840000
b1000000000000000 !
b1000000000000000 )
b1000 "
b1000 '
b1000 &
#1850000
b1000000000000000 !
b1000000000000000 )
b1001 "
b1001 '
b1001 &
#1860000
b1000000000000000 !
b1000000000000000 )
b1010 "
b1010 '
b1010 &
#1870000
b1000000000000000 !
b1000000000000000 )
b1011 "
b1011 '
b1011 &
#1880000
b1000000000000000 !
b1000000000000000 )
b1100 "
b1100 '
b1100 &
#1890000
b1000000000000000 !
b1000000000000000 )
b1101 "
b1101 '
b1101 &
#1900000
b1000000000000000 !
b1000000000000000 )
b1110 "
b1110 '
b1110 &
#1910000
b1000000000000000 !
b1000000000000000 )
b1111 "
b1111 '
b1111 &
#1920000
b1000000000000000 !
b1000000000000000 )
b0 "
b0 '
b110000000000000000000000001 #
b110000000000000000000000001 (
b1100 %
b0 &
#1930000
b1000000000000000 !
b1000000000000000 )
b1 "
b1 '
b1 &
#1940000
b1000000000000000 !
b1000000000000000 )
b10 "
b10 '
b10 &
#1950000
b1000000000000000 !
b1000000000000000 )
b11 "
b11 '
b11 &
#1960000
b1000000000000000 !
b1000000000000000 )
b100 "
b100 '
b100 &
#1970000
b1000000000000000 !
b1000000000000000 )
b101 "
b101 '
b101 &
#1980000
b1000000000000000 !
b1000000000000000 )
b110 "
b110 '
b110 &
#1990000
b1000000000000000 !
b1000000000000000 )
b111 "
b111 '
b111 &
#2000000
b1000000000000000 !
b1000000000000000 )
b1000 "
b1000 '
b1000 &
#2010000
b1000000000000000 !
b1000000000000000 )
b1001 "
b1001 '
b1001 &
#2020000
b1000000000000000 !
b1000000000000000 )
b1010 "
b1010 '
b1010 &
#2030000
b1000000000000000 !
b1000000000000000 )
b1011 "
b1011 '
b1011 &
#2040000
b1000000000000000 !
b1000000000000000 )
b1100 "
b1100 '
b1100 &
#2050000
b1000000000000000 !
b1000000000000000 )
b1101 "
b1101 '
b1101 &
#2060000
b1000000000000000 !
b1000000000000000 )
b1110 "
b1110 '
b1110 &
#2070000
b1000000000000000 !
b1000000000000000 )
b1111 "
b1111 '
b1111 &
#2080000
b1000000000000000 !
b1000000000000000 )
b0 "
b0 '
b110100000000000000000000001 #
b110100000000000000000000001 (
b1101 %
b0 &
#2090000
b1000000000000000 !
b1000000000000000 )
b1 "
b1 '
b1 &
#2100000
b1000000000000000 !
b1000000000000000 )
b10 "
b10 '
b10 &
#2110000
b1000000000000000 !
b1000000000000000 )
b11 "
b11 '
b11 &
#2120000
b1000000000000000 !
b1000000000000000 )
b100 "
b100 '
b100 &
#2130000
b1000000000000000 !
b1000000000000000 )
b101 "
b101 '
b101 &
#2140000
b1000000000000000 !
b1000000000000000 )
b110 "
b110 '
b110 &
#2150000
b1000000000000000 !
b1000000000000000 )
b111 "
b111 '
b111 &
#2160000
b1000000000000000 !
b1000000000000000 )
b1000 "
b1000 '
b1000 &
#2170000
b1000000000000000 !
b1000000000000000 )
b1001 "
b1001 '
b1001 &
#2180000
b1000000000000000 !
b1000000000000000 )
b1010 "
b1010 '
b1010 &
#2190000
b1000000000000000 !
b1000000000000000 )
b1011 "
b1011 '
b1011 &
#2200000
b1000000000000000 !
b1000000000000000 )
b1100 "
b1100 '
b1100 &
#2210000
b1000000000000000 !
b1000000000000000 )
b1101 "
b1101 '
b1101 &
#2220000
b1000000000000000 !
b1000000000000000 )
b1110 "
b1110 '
b1110 &
#2230000
b1000000000000000 !
b1000000000000000 )
b1111 "
b1111 '
b1111 &
#2240000
b1000000000000000 !
b1000000000000000 )
b0 "
b0 '
b111000000000000000000000001 #
b111000000000000000000000001 (
b1110 %
b0 &
#2250000
b1000000000000000 !
b1000000000000000 )
b1 "
b1 '
b1 &
#2260000
b1000000000000000 !
b1000000000000000 )
b10 "
b10 '
b10 &
#2270000
b1000000000000000 !
b1000000000000000 )
b11 "
b11 '
b11 &
#2280000
b1000000000000000 !
b1000000000000000 )
b100 "
b100 '
b100 &
#2290000
b1000000000000000 !
b1000000000000000 )
b101 "
b101 '
b101 &
#2300000
b1000000000000000 !
b1000000000000000 )
b110 "
b110 '
b110 &
#2310000
b1000000000000000 !
b1000000000000000 )
b111 "
b111 '
b111 &
#2320000
b1000000000000000 !
b1000000000000000 )
b1000 "
b1000 '
b1000 &
#2330000
b1000000000000000 !
b1000000000000000 )
b1001 "
b1001 '
b1001 &
#2340000
b1000000000000000 !
b1000000000000000 )
b1010 "
b1010 '
b1010 &
#2350000
b1000000000000000 !
b1000000000000000 )
b1011 "
b1011 '
b1011 &
#2360000
b1000000000000000 !
b1000000000000000 )
b1100 "
b1100 '
b1100 &
#2370000
b1000000000000000 !
b1000000000000000 )
b1101 "
b1101 '
b1101 &
#2380000
b1000000000000000 !
b1000000000000000 )
b1110 "
b1110 '
b1110 &
#2390000
b1000000000000000 !
b1000000000000000 )
b1111 "
b1111 '
b1111 &
#2400000
b1000000000000000 !
b1000000000000000 )
b0 "
b0 '
b111100000000000000000000001 #
b111100000000000000000000001 (
b1111 %
b0 &
#2410000
b1000000000000000 !
b1000000000000000 )
b1 "
b1 '
b1 &
#2420000
b1000000000000000 !
b1000000000000000 )
b10 "
b10 '
b10 &
#2430000
b1000000000000000 !
b1000000000000000 )
b11 "
b11 '
b11 &
#2440000
b1000000000000000 !
b1000000000000000 )
b100 "
b100 '
b100 &
#2450000
b1000000000000000 !
b1000000000000000 )
b101 "
b101 '
b101 &
#2460000
b1000000000000000 !
b1000000000000000 )
b110 "
b110 '
b110 &
#2470000
b1000000000000000 !
b1000000000000000 )
b111 "
b111 '
b111 &
#2480000
b1000000000000000 !
b1000000000000000 )
b1000 "
b1000 '
b1000 &
#2490000
b1000000000000000 !
b1000000000000000 )
b1001 "
b1001 '
b1001 &
#2500000
b1000000000000000 !
b1000000000000000 )
b1010 "
b1010 '
b1010 &
#2510000
b1000000000000000 !
b1000000000000000 )
b1011 "
b1011 '
b1011 &
#2520000
b1000000000000000 !
b1000000000000000 )
b1100 "
b1100 '
b1100 &
#2530000
b1000000000000000 !
b1000000000000000 )
b1101 "
b1101 '
b1101 &
#2540000
b1000000000000000 !
b1000000000000000 )
b1110 "
b1110 '
b1110 &
#2550000
b1000000000000000 !
b1000000000000000 )
b1111 "
b1111 '
b1111 &
#2560000
b1000000000001000 !
b1000000000001000 )
b0 "
b0 '
b10 #
b10 (
b1 $
b0 %
b0 &
#2570000
b1000000000001000 !
b1000000000001000 )
b1 "
b1 '
b1 &
#2580000
b1000000000001000 !
b1000000000001000 )
b10 "
b10 '
b10 &
#2590000
b1000000000001000 !
b1000000000001000 )
b11 "
b11 '
b11 &
#2600000
b1000000000001000 !
b1000000000001000 )
b100 "
b100 '
b100 &
#2610000
b1000000000001000 !
b1000000000001000 )
b101 "
b101 '
b101 &
#2620000
b1000000000001000 !
b1000000000001000 )
b110 "
b110 '
b110 &
#2630000
b1000000000001000 !
b1000000000001000 )
b111 "
b111 '
b111 &
#2640000
b1000000000001000 !
b1000000000001000 )
b1000 "
b1000 '
b1000 &
#2650000
b1000000000001000 !
b1000000000001000 )
b1001 "
b1001 '
b1001 &
#2660000
b1000000000001000 !
b1000000000001000 )
b1010 "
b1010 '
b1010 &
#2670000
b1000000000001000 !
b1000000000001000 )
b1011 "
b1011 '
b1011 &
#2680000
b1000000000001000 !
b1000000000001000 )
b1100 "
b1100 '
b1100 &
#2690000
b1000000000001000 !
b1000000000001000 )
b1101 "
b1101 '
b1101 &
#2700000
b1000000000001000 !
b1000000000001000 )
b1110 "
b1110 '
b1110 &
#2710000
b1000000000001000 !
b1000000000001000 )
b1111 "
b1111 '
b1111 &
#2720000
b1000000000001000 !
b1000000000001000 )
b0 "
b0 '
b100000000000000000000010 #
b100000000000000000000010 (
b1 %
b0 &
#2730000
b1000000000001000 !
b1000000000001000 )
b1 "
b1 '
b1 &
#2740000
b1000000000001000 !
b1000000000001000 )
b10 "
b10 '
b10 &
#2750000
b1000000000001000 !
b1000000000001000 )
b11 "
b11 '
b11 &
#2760000
b1000000000001000 !
b1000000000001000 )
b100 "
b100 '
b100 &
#2770000
b1000000000001000 !
b1000000000001000 )
b101 "
b101 '
b101 &
#2780000
b1000000000001000 !
b1000000000001000 )
b110 "
b110 '
b110 &
#2790000
b1000000000001000 !
b1000000000001000 )
b111 "
b111 '
b111 &
#2800000
b1000000000001000 !
b1000000000001000 )
b1000 "
b1000 '
b1000 &
#2810000
b1000000000001000 !
b1000000000001000 )
b1001 "
b1001 '
b1001 &
#2820000
b1000000000001000 !
b1000000000001000 )
b1010 "
b1010 '
b1010 &
#2830000
b1000000000001000 !
b1000000000001000 )
b1011 "
b1011 '
b1011 &
#2840000
b1000000000001000 !
b1000000000001000 )
b1100 "
b1100 '
b1100 &
#2850000
b1000000000001000 !
b1000000000001000 )
b1101 "
b1101 '
b1101 &
#2860000
b1000000000001000 !
b1000000000001000 )
b1110 "
b1110 '
b1110 &
#2870000
b1000000000001000 !
b1000000000001000 )
b1111 "
b1111 '
b1111 &
#2880000
b1000000000001000 !
b1000000000001000 )
b0 "
b0 '
b1000000000000000000000010 #
b1000000000000000000000010 (
b10 %
b0 &
#2890000
b1000000000001000 !
b1000000000001000 )
b1 "
b1 '
b1 &
#2900000
b1000000000001000 !
b1000000000001000 )
b10 "
b10 '
b10 &
#2910000
b1000000000001000 !
b1000000000001000 )
b11 "
b11 '
b11 &
#2920000
b1000000000001000 !
b1000000000001000 )
b100 "
b100 '
b100 &
#2930000
b1000000000001000 !
b1000000000001000 )
b101 "
b101 '
b101 &
#2940000
b1000000000001000 !
b1000000000001000 )
b110 "
b110 '
b110 &
#2950000
b1000000000001000 !
b1000000000001000 )
b111 "
b111 '
b111 &
#2960000
b1000000000001000 !
b1000000000001000 )
b1000 "
b1000 '
b1000 &
#2970000
b1000000000001000 !
b1000000000001000 )
b1001 "
b1001 '
b1001 &
#2980000
b1000000000001000 !
b1000000000001000 )
b1010 "
b1010 '
b1010 &
#2990000
b1000000000001000 !
b1000000000001000 )
b1011 "
b1011 '
b1011 &
#3000000
b1000000000001000 !
b1000000000001000 )
b1100 "
b1100 '
b1100 &
#3010000
b1000000000001000 !
b1000000000001000 )
b1101 "
b1101 '
b1101 &
#3020000
b1000000000001000 !
b1000000000001000 )
b1110 "
b1110 '
b1110 &
#3030000
b1000000000001000 !
b1000000000001000 )
b1111 "
b1111 '
b1111 &
#3040000
b1000000000001000 !
b1000000000001000 )
b0 "
b0 '
b1100000000000000000000010 #
b1100000000000000000000010 (
b11 %
b0 &
